aetos/__init__.py
aetos/api-paste.ini
aetos/app.py
aetos/hooks.py
aetos/i18n.py
aetos/middleware.py
aetos/opts.py
aetos/policies.py
aetos/rbac.py
aetos/service.py
aetos/version.py
aetos/conf/__init__.py
aetos/conf/defaults.py
aetos/controllers/__init__.py
aetos/controllers/root.py
aetos/controllers/api/__init__.py
aetos/controllers/api/v1/__init__.py
aetos/controllers/api/v1/base.py
aetos/controllers/api/v1/label.py
aetos/controllers/api/v1/labels.py
aetos/controllers/api/v1/query.py
aetos/controllers/api/v1/root.py
aetos/controllers/api/v1/series.py
aetos/controllers/api/v1/status.py
aetos/controllers/api/v1/targets.py
aetos/controllers/api/v1/admin/__init__.py
aetos/controllers/api/v1/admin/root.py
aetos/controllers/api/v1/admin/tsdb/__init__.py
aetos/controllers/api/v1/admin/tsdb/clean_tombstones.py
aetos/controllers/api/v1/admin/tsdb/delete_series.py
aetos/controllers/api/v1/admin/tsdb/root.py
aetos/controllers/api/v1/admin/tsdb/snapshot.py
aetos/tests/__init__.py
aetos/tests/base.py
aetos/tests/functional/__init__.py
aetos/tests/functional/base.py
aetos/tests/functional/policy.yaml-test
aetos/tests/functional/test_admin_endpoints.py
aetos/tests/functional/test_core_endpoints.py
aetos/tests/unit/__init__.py
aetos/tests/unit/test_base_controller.py
aetos/wsgi/__init__.py
aetos/wsgi/api.py
aetos-1.0.0.data/data/etc/aetos/aetos-config-generator.conf
aetos-1.0.0.data/data/etc/aetos/aetos-policy-generator.conf
aetos-1.0.0.data/scripts/aetos
aetos-1.0.0.dist-info/AUTHORS
aetos-1.0.0.dist-info/LICENSE
aetos-1.0.0.dist-info/METADATA
aetos-1.0.0.dist-info/WHEEL
aetos-1.0.0.dist-info/entry_points.txt
aetos-1.0.0.dist-info/pbr.json
aetos-1.0.0.dist-info/top_level.txt
aetos-1.0.0.dist-info/RECORD
